<?xml version="1.0" encoding="UTF-8" standalone="yes"?>
<game>
    <head>
        <title>SQL Flight - T03</title>
        <teaser>Escape SQL Island by plane</teaser>
        <copyright>Audrey Anna Blein, Curtis Mellsop, Joel Mullarkey, Nicolas Neeser, Jibin Mathew Peechatt</copyright>
    </head>
    <scenes>
        <text-scene>
            <text>You have freed the pilot Arthur Tailor from captivity on SQL Island, good job! He agrees to fly you to the mainland on an old Airbus A320 - but there are limited seats. You need to choose your passengers wisely.</text>
        </text-scene>
        <text-scene>
            <text>Arthur hands you the passenger manifest. Before you decide who boards, take a look at who is waiting on the runway.</text>
        </text-scene>
        <select-scene is-row-order-relevant="false" is-col-order-relevant="false" are-col-names-relevant="false">
            <text>Challenge 0: Display all passengers from the Passenger table so you can see who is available.</text>
            <sql-solution>SELECT * FROM Passenger</sql-solution>
            <sql-placeholder>SELECT * FROM ...</sql-placeholder>
        </select-scene>
        <text-scene>
            <text>The flight costs at least 1000 coins per person, and you want passengers who bring useful skills for the journey. Let&#x27;s check who qualifies.</text>
        </text-scene>
        <select-scene is-row-order-relevant="false" is-col-order-relevant="false" are-col-names-relevant="false">
            <text>Find all passengers who can afford the trip (money &gt;= 1000) AND have a skill. Remember to check the 'Schema' below.</text>
            <sql-solution>SELECT * FROM Passenger WHERE money &gt;= 1000 AND skill IS NOT NULL</sql-solution>
            <sql-placeholder>SELECT * FROM Passenger WHERE ...</sql-placeholder>
        </select-scene>
        <text-scene>
            <text>Excellent! Marco, Sandra, Lina, Julia, and Aisha are boarding. The Airbus A320 roars to life and you take off from SQL Island!</text>
        </text-scene>
        <select-scene is-row-order-relevant="false" is-col-order-relevant="false" are-col-names-relevant="true">
            <text>Before serving meals, you need a passenger overview. Count the total number of passengers, how many have a skill, and how many have allergies. Use the FILTER clause! Name the columns: total, with_skill, with_allergy. Hint: the syntax reads FILTER (WHERE ...)</text>
            <sql-solution>SELECT COUNT(*) AS total, COUNT(*) FILTER (WHERE skill IS NOT NULL) AS with_skill, COUNT(*) FILTER (WHERE allergy IS NOT NULL) AS with_allergy FROM Passenger</sql-solution>
            <sql-placeholder>SELECT COUNT(*) AS total, COUNT(*) FILTER (...) AS with_skill, COUNT(*) FILTER (...) AS with_allergy FROM Passenger</sql-placeholder>
        </select-scene>
        <text-scene>
            <text>5 out of 8 passengers have allergies - that&#x27;s a lot! You start distributing the meals carefully. The pilot Arthur grabs the Salmon Teriyaki from the galley before you can stop him...</text>
        </text-scene>
        <text-scene>
            <text>Arthur collapses! The Salmon Teriyaki contains shellfish, and he&#x27;s severely allergic! The pilot is unconscious. You need to take control of the plane!</text>
        </text-scene>
        <select-scene is-row-order-relevant="false" is-col-order-relevant="false" are-col-names-relevant="true">
            <text>First, check the meal situation on our plane (planeid = 1). Count the total meals, how many are safe for everyone (contains IS NULL), and how many contain allergens. Use the FILTER clause! Name the columns: total_meals, safe_for_all, has_allergens</text>
            <sql-solution>SELECT COUNT(*) AS total_meals, COUNT(*) FILTER (WHERE contains IS NULL) AS safe_for_all, COUNT(*) FILTER (WHERE contains IS NOT NULL) AS has_allergens FROM Meal WHERE planeid = 1</sql-solution>
            <sql-placeholder>SELECT COUNT(*) AS total_meals, COUNT(*) FILTER (...) AS safe_for_all, COUNT(*) FILTER (...) AS has_allergens FROM ...</sql-placeholder>
        </select-scene>
        <text-scene>
            <text>OK, only 2 out of 4 meals are safe for everyone. You hand those out first. Now you grab the controls. The fuel gauge reads 62.5% - that gives you roughly a 700 km range. You need to find an airport to land!</text>
        </text-scene>
        <select-scene is-row-order-relevant="false" is-col-order-relevant="false" are-col-names-relevant="true">
            <text>Emergency check! Count how many airports are reachable (distance &gt; 0 AND distance &lt;= 700) versus out of reach (distance &gt; 700). Use the FILTER clause! Name the columns: reachable, out_of_reach</text>
            <sql-solution>SELECT COUNT(*) FILTER (WHERE distance &gt; 0 AND distance &lt;= 700) AS reachable, COUNT(*) FILTER (WHERE distance &gt; 700) AS out_of_reach FROM Airport</sql-solution>
            <sql-placeholder>SELECT COUNT(*) FILTER (...) AS reachable, COUNT(*) FILTER (...) AS out_of_reach FROM Airport</sql-placeholder>
        </select-scene>
        <text-scene>
            <text>5 airports are within range, 2 are too far. Now list them so you can pick the closest one for your emergency landing!</text>
        </text-scene>
        <select-scene is-row-order-relevant="true" is-col-order-relevant="false" are-col-names-relevant="false">
            <text>List the name and distance of all reachable airports (distance &gt; 0 AND distance &lt;= 700), sorted by distance from closest to farthest.</text>
            <sql-solution>SELECT name, distance FROM Airport WHERE distance &gt; 0 AND distance &lt;= 700 ORDER BY distance ASC</sql-solution>
            <sql-placeholder>SELECT name, distance FROM Airport WHERE ... ORDER BY ...</sql-placeholder>
        </select-scene>
        <text-scene>
            <text>George F.L. Charles Airport on Saint Lucia, only 224 km away! You bank the plane hard to the left and begin your descent. Sandra uses her navigation skills to guide you, while Lina keeps the engines running with her mechanics know-how. The runway appears through the clouds...</text>
        </text-scene>
        <text-scene>
            <text>TOUCHDOWN! You&#x27;ve landed the Airbus safely on Saint Lucia! The passengers erupt in cheers. Arthur is rushed to hospital. But the paperwork has only just begun...</text>
        </text-scene>
        <text-scene>
            <text>The airline&#x27;s insurance team rushes over with clipboards. They need a financial breakdown of the passengers immediately - specifically how passengers with useful skills compare financially to those without.</text>
        </text-scene>
        <select-scene is-row-order-relevant="false" is-col-order-relevant="false" are-col-names-relevant="true">
            <text>Calculate the total and average money for passengers WITH a skill and for those WITHOUT a skill. Use SUM() and AVG() with the FILTER clause! Name the columns: skilled_total, skilled_avg, unskilled_total, unskilled_avg</text>
            <sql-solution>SELECT SUM(money) FILTER (WHERE skill IS NOT NULL) AS skilled_total, AVG(money) FILTER (WHERE skill IS NOT NULL) AS skilled_avg, SUM(money) FILTER (WHERE skill IS NULL) AS unskilled_total, AVG(money) FILTER (WHERE skill IS NULL) AS unskilled_avg FROM Passenger</sql-solution>
            <sql-placeholder>SELECT SUM(...) FILTER (...) AS skilled_total, AVG(...) FILTER (...) AS skilled_avg, SUM(...) FILTER (...) AS unskilled_total, AVG(...) FILTER (...) AS unskilled_avg FROM Passenger</sql-placeholder>
        </select-scene>
        <text-scene>
            <text>Insurance report submitted! Now the Saint Lucia airport authority wants a fleet-wide meal safety audit. They need to know, for every plane in the fleet, how many meals are allergen-free versus potentially dangerous.</text>
        </text-scene>
        <select-scene is-row-order-relevant="false" is-col-order-relevant="false" are-col-names-relevant="true">
            <text>For each plane, show the planeid and count: total meals, how many are safe for all (contains IS NULL), and how many contain allergens (contains IS NOT NULL). Use FILTER together with GROUP BY! Name the columns: planeid, total_meals, safe_meals, allergen_meals</text>
            <sql-solution>SELECT planeid, COUNT(*) AS total_meals, COUNT(*) FILTER (WHERE contains IS NULL) AS safe_meals, COUNT(*) FILTER (WHERE contains IS NOT NULL) AS allergen_meals FROM Meal GROUP BY planeid ORDER BY planeid</sql-solution>
            <sql-placeholder>SELECT planeid, COUNT(*) AS total_meals, COUNT(*) FILTER (...) AS safe_meals, COUNT(*) FILTER (...) AS allergen_meals FROM Meal GROUP BY planeid ORDER BY planeid</sql-placeholder>
        </select-scene>
        <text-scene>
            <text>Fleet safety report filed! Arthur makes a full recovery at hospital. The whole crew is hailed as heroes. You&#x27;ve not only escaped SQL Island - you&#x27;ve mastered the FILTER clause! Congratulations, Captain!</text>
        </text-scene>
    </scenes>
    <initial-sql-script>CREATE TABLE Passenger (
    passengerid SERIAL PRIMARY KEY,
    name TEXT NOT NULL,
    money INTEGER NOT NULL,
    skill TEXT,
    allergy TEXT
);

CREATE TABLE Plane (
    planeid SERIAL PRIMARY KEY,
    model TEXT NOT NULL,
    fuel_level NUMERIC(5,2) NOT NULL,
    fuel_min NUMERIC(5,2) NOT NULL,
    fuel_max NUMERIC(5,2) NOT NULL,
    altitude INTEGER NOT NULL,
    altitude_min INTEGER NOT NULL,
    altitude_max INTEGER NOT NULL,
    cabin_pressure NUMERIC(4,2) NOT NULL,
    cabin_pressure_min NUMERIC(4,2) NOT NULL,
    cabin_pressure_max NUMERIC(4,2) NOT NULL,
    speed INTEGER NOT NULL,
    speed_min INTEGER NOT NULL,
    speed_max INTEGER NOT NULL
);

CREATE TABLE Meal (
    mealid SERIAL PRIMARY KEY,
    planeid INTEGER NOT NULL
        REFERENCES Plane(planeid),
    name TEXT NOT NULL,
    contains TEXT
);

CREATE TABLE Airport (
    airportid SERIAL PRIMARY KEY,
    name TEXT NOT NULL,
    distance INTEGER NOT NULL
);

INSERT INTO Passenger (name, money, skill, allergy)
VALUES
(&#x27;Marco Zeller&#x27;, 1200, &#x27;first aid&#x27;, NULL),
(&#x27;Sandra Kluge&#x27;, 3400, &#x27;navigation&#x27;, &#x27;gluten&#x27;),
(&#x27;Tomas Berger&#x27;, 800, NULL, &#x27;nuts&#x27;),
(&#x27;Lina Fischer&#x27;, 5200, &#x27;mechanics&#x27;, NULL),
(&#x27;Reto Ammann&#x27;, 150, &#x27;cooking&#x27;, &#x27;dairy&#x27;),
(&#x27;Julia Hartmann&#x27;, 2750, &#x27;first aid&#x27;, &#x27;shellfish&#x27;),
(&#x27;Niklas Stein&#x27;, 960, NULL, NULL),
(&#x27;Aisha Mirza&#x27;, 4100, &#x27;electronics&#x27;, &#x27;eggs&#x27;);

INSERT INTO Plane (model, fuel_level, fuel_min, fuel_max, altitude, altitude_min, altitude_max, cabin_pressure, cabin_pressure_min, cabin_pressure_max, speed, speed_min, speed_max)
VALUES
(&#x27;Airbus A320&#x27;, 62.50, 10.00, 100.00, 35000, 20000, 42000, 0.85, 0.75, 1.00, 480, 200, 575),
(&#x27;Boeing 737&#x27;, 45.30, 10.00, 100.00, 31000, 20000, 41000, 0.82, 0.75, 1.00, 460, 200, 544),
(&#x27;Embraer E190&#x27;, 78.10, 10.00, 100.00, 28000, 15000, 39000, 0.88, 0.75, 1.00, 430, 180, 510);

INSERT INTO Meal (planeid, name, contains)
VALUES
(1, &#x27;Grilled Chicken Wrap&#x27;, &#x27;gluten&#x27;),
(1, &#x27;Vegetable Curry&#x27;, NULL),
(1, &#x27;Salmon Teriyaki&#x27;, &#x27;shellfish&#x27;),
(1, &#x27;Fruit Plate&#x27;, NULL),
(2, &#x27;Beef Lasagna&#x27;, &#x27;gluten,dairy&#x27;),
(2, &#x27;Thai Green Curry&#x27;, &#x27;nuts&#x27;),
(2, &#x27;Caesar Salad&#x27;, &#x27;eggs,dairy&#x27;),
(3, &#x27;Mushroom Risotto&#x27;, &#x27;dairy&#x27;),
(3, &#x27;Grilled Tofu Bowl&#x27;, NULL),
(3, &#x27;Pancakes with Berries&#x27;, &#x27;gluten,eggs,dairy&#x27;);

INSERT INTO Airport (name, distance)
VALUES
(&#x27;SQL Island&#x27;, 0),
(&#x27;G.F.L. Charles&#x27;, 224),
(&#x27;Maurice Bishop&#x27;, 612),
(&#x27;Princess Juliana&#x27;, 305),
(&#x27;Piarco&#x27;, 688),
(&#x27;Argyle Internati.&#x27;, 843),
(&#x27;Clayton J. Lloyd&#x27;, 621),
(&#x27;Miami Internat.&#x27;, 1860);</initial-sql-script>
</game>
